aquacheck/__init__.py
aquacheck/main.py
DriniChlor-0.0.3.dist-info/LICENSE
DriniChlor-0.0.3.dist-info/METADATA
DriniChlor-0.0.3.dist-info/WHEEL
DriniChlor-0.0.3.dist-info/top_level.txt
DriniChlor-0.0.3.dist-info/RECORD
